alpha_pca/__init__.py
alpha_pca/alpha_pca.py
alpha_pca-1.0.2.dist-info/LICENSE.txt
alpha_pca-1.0.2.dist-info/METADATA
alpha_pca-1.0.2.dist-info/WHEEL
alpha_pca-1.0.2.dist-info/top_level.txt
alpha_pca-1.0.2.dist-info/RECORD
