Metadata-Version: 2.1
Name: alpha-pca
Version: 1.0.2
Summary: Phi-Alpha PCA
Home-page: 
Author: Charles Condevaux
Author-email: charles.condevaux@gmail.com
Classifier: Programming Language :: Python :: 3
Classifier: License :: OSI Approved :: MIT License
Classifier: Operating System :: OS Independent
Requires-Python: >=3.7
License-File: LICENSE.txt
Requires-Dist: torch (>=1.7)
Requires-Dist: scikit-learn (>=1.0)
